finance_news_api-1.0.2.dist-info/licenses/LICENSE
newsapi2/LICENSE
newsapi2/__init__.py
newsapi2/auth.py
newsapi2/config.py
newsapi2/database.py
newsapi2/exceptions.py
newsapi2/logging_config.py
newsapi2/main.py
newsapi2/models.py
newsapi2/schemas.py
newsapi2/path/to/venv/lib/python3.13/site-packages/annotated_types-0.7.0.dist-info/licenses/LICENSE
newsapi2/path/to/venv/lib/python3.13/site-packages/attrs-25.3.0.dist-info/licenses/LICENSE
newsapi2/path/to/venv/lib/python3.13/site-packages/beautifulsoup4-4.13.4.dist-info/licenses/LICENSE
newsapi2/path/to/venv/lib/python3.13/site-packages/certifi-2025.4.26.dist-info/licenses/LICENSE
newsapi2/path/to/venv/lib/python3.13/site-packages/charset_normalizer-3.4.2.dist-info/licenses/LICENSE
newsapi2/path/to/venv/lib/python3.13/site-packages/curl_cffi-0.11.1.dist-info/licenses/LICENSE
newsapi2/path/to/venv/lib/python3.13/site-packages/fastapi-0.115.12.dist-info/licenses/LICENSE
newsapi2/path/to/venv/lib/python3.13/site-packages/frozenlist-1.6.0.dist-info/licenses/LICENSE
newsapi2/path/to/venv/lib/python3.13/site-packages/greenlet-3.2.2.dist-info/licenses/LICENSE
newsapi2/path/to/venv/lib/python3.13/site-packages/iniconfig-2.1.0.dist-info/licenses/LICENSE
newsapi2/path/to/venv/lib/python3.13/site-packages/multidict-6.4.3.dist-info/licenses/LICENSE
newsapi2/path/to/venv/lib/python3.13/site-packages/numpy/ma/LICENSE
newsapi2/path/to/venv/lib/python3.13/site-packages/packaging-25.0.dist-info/licenses/LICENSE
newsapi2/path/to/venv/lib/python3.13/site-packages/peewee-3.18.1.dist-info/licenses/LICENSE
newsapi2/path/to/venv/lib/python3.13/site-packages/platformdirs-4.3.8.dist-info/licenses/LICENSE
newsapi2/path/to/venv/lib/python3.13/site-packages/playwright/driver/LICENSE
newsapi2/path/to/venv/lib/python3.13/site-packages/playwright-1.52.0.dist-info/licenses/LICENSE
newsapi2/path/to/venv/lib/python3.13/site-packages/pluggy-1.6.0.dist-info/licenses/LICENSE
newsapi2/path/to/venv/lib/python3.13/site-packages/propcache-0.3.1.dist-info/licenses/LICENSE
newsapi2/path/to/venv/lib/python3.13/site-packages/pydantic-2.11.4.dist-info/licenses/LICENSE
newsapi2/path/to/venv/lib/python3.13/site-packages/pydantic_core-2.33.2.dist-info/licenses/LICENSE
newsapi2/path/to/venv/lib/python3.13/site-packages/pytest_asyncio-0.26.0.dist-info/licenses/LICENSE
newsapi2/path/to/venv/lib/python3.13/site-packages/pytest_cov-6.1.1.dist-info/licenses/LICENSE
newsapi2/path/to/venv/lib/python3.13/site-packages/python_dotenv-1.1.0.dist-info/licenses/LICENSE
newsapi2/path/to/venv/lib/python3.13/site-packages/typing_extensions-4.13.2.dist-info/licenses/LICENSE
newsapi2/path/to/venv/lib/python3.13/site-packages/typing_inspection-0.4.0.dist-info/licenses/LICENSE
newsapi2/path/to/venv/lib/python3.13/site-packages/tzdata-2025.2.dist-info/licenses/LICENSE
newsapi2/path/to/venv/lib/python3.13/site-packages/yarl-1.20.0.dist-info/licenses/LICENSE
newsapi2/templates/admin.html
finance_news_api-1.0.2.dist-info/METADATA
finance_news_api-1.0.2.dist-info/WHEEL
finance_news_api-1.0.2.dist-info/entry_points.txt
finance_news_api-1.0.2.dist-info/top_level.txt
newsapi2/path/to/venv/lib/python3.13/site-packages/Brotli-1.1.0.dist-info/LICENSE
newsapi2/path/to/venv/lib/python3.13/site-packages/PyYAML-6.0.2.dist-info/LICENSE
newsapi2/path/to/venv/lib/python3.13/site-packages/aiohappyeyeballs-2.6.1.dist-info/LICENSE
newsapi2/path/to/venv/lib/python3.13/site-packages/aioresponses-0.7.8.dist-info/LICENSE
newsapi2/path/to/venv/lib/python3.13/site-packages/aiosignal-1.3.2.dist-info/LICENSE
newsapi2/path/to/venv/lib/python3.13/site-packages/anyio-4.9.0.dist-info/LICENSE
newsapi2/path/to/venv/lib/python3.13/site-packages/cffi-1.17.1.dist-info/LICENSE
newsapi2/path/to/venv/lib/python3.13/site-packages/feedparser-6.0.11.dist-info/LICENSE
newsapi2/path/to/venv/lib/python3.13/site-packages/pandas-2.2.3.dist-info/LICENSE
newsapi2/path/to/venv/lib/python3.13/site-packages/protobuf-6.31.0.dist-info/LICENSE
newsapi2/path/to/venv/lib/python3.13/site-packages/pycparser-2.22.dist-info/LICENSE
newsapi2/path/to/venv/lib/python3.13/site-packages/pyee-13.0.0.dist-info/LICENSE
newsapi2/path/to/venv/lib/python3.13/site-packages/pytest-8.3.5.dist-info/LICENSE
newsapi2/path/to/venv/lib/python3.13/site-packages/pytest_mock-3.14.0.dist-info/LICENSE
newsapi2/path/to/venv/lib/python3.13/site-packages/python_dateutil-2.9.0.post0.dist-info/LICENSE
newsapi2/path/to/venv/lib/python3.13/site-packages/requests-2.32.3.dist-info/LICENSE
newsapi2/path/to/venv/lib/python3.13/site-packages/responses-0.25.7.dist-info/LICENSE
newsapi2/path/to/venv/lib/python3.13/site-packages/six-1.17.0.dist-info/LICENSE
newsapi2/path/to/venv/lib/python3.13/site-packages/sniffio-1.3.1.dist-info/LICENSE
newsapi2/path/to/venv/lib/python3.13/site-packages/textblob-0.19.0.dist-info/LICENSE
newsapi2/path/to/venv/lib/python3.13/site-packages/websockets-15.0.1.dist-info/LICENSE
finance_news_api-1.0.2.dist-info/RECORD
