Metadata-Version: 2.4
Name: finance-news-api
Version: 1.0.2
Summary: A powerful API that aggregates financial news and provides comprehensive market sentiment analysis
Home-page: https://github.com/pratyushkhanal/finance-news-api
Author: Pratyush Khanal
Author-email: pratyushkhanal@gmail.com
License: Apache-2.0
Project-URL: Bug Tracker, https://github.com/pratyushkhanal/finance-news-api/issues
Classifier: Development Status :: 4 - Beta
Classifier: Intended Audience :: Developers
Classifier: Intended Audience :: Financial and Insurance Industry
Classifier: Programming Language :: Python :: 3
Classifier: Programming Language :: Python :: 3.8
Classifier: Programming Language :: Python :: 3.9
Classifier: Programming Language :: Python :: 3.10
Classifier: Programming Language :: Python :: 3.11
Classifier: Operating System :: OS Independent
Requires-Python: >=3.8
License-File: LICENSE
Requires-Dist: fastapi>=0.68.0
Requires-Dist: uvicorn>=0.15.0
Requires-Dist: python-dotenv>=0.19.0
Requires-Dist: peewee>=3.14.0
Requires-Dist: pydantic>=2.0.0
Requires-Dist: requests>=2.26.0
Requires-Dist: beautifulsoup4>=4.9.3
Requires-Dist: feedparser>=6.0.8
Requires-Dist: pandas>=1.3.0
Requires-Dist: numpy>=1.21.0
Requires-Dist: textblob>=0.15.3
Requires-Dist: python-jose[cryptography]>=3.3.0
Requires-Dist: passlib[bcrypt]>=1.7.4
Requires-Dist: python-multipart>=0.0.5
Requires-Dist: aiohttp>=3.8.0
Requires-Dist: playwright>=1.0.0
Requires-Dist: curl-cffi>=0.5.0
Provides-Extra: dev
Requires-Dist: pytest; extra == "dev"
Requires-Dist: httpx; extra == "dev"
Requires-Dist: pytest-asyncio; extra == "dev"
Requires-Dist: pytest-mock; extra == "dev"
Requires-Dist: pytest-cov; extra == "dev"
Requires-Dist: aioresponses; extra == "dev"
Requires-Dist: responses; extra == "dev"
Dynamic: author
Dynamic: author-email
Dynamic: classifier
Dynamic: description
Dynamic: description-content-type
Dynamic: home-page
Dynamic: license
Dynamic: license-file
Dynamic: project-url
Dynamic: provides-extra
Dynamic: requires-dist
Dynamic: requires-python
Dynamic: summary
